[
  {
    "Id": 100101,
    "Rarity": 3,
    "RaceDressId": "100101",
    "ProperDistanceShort": 2,
    "ProperDistanceMile": 5,
    "ProperDistanceMiddle": 7,
    "ProperDistanceLong": 7,
    "ProperRunningStyleNige": 1,
    "ProperRunningStyleSenko": 7,
    "ProperRunningStyleSashi": 7,
    "ProperRunningStyleOikomi": 5,
    "ProperGroundTurf": 7,
    "ProperGroundDirt": 1
  },
  {
    "Id": 100102,
    "Rarity": 3,
    "RaceDressId": "100130",
    "ProperDistanceShort": 2,
    "ProperDistanceMile": 5,
    "ProperDistanceMiddle": 7,
    "ProperDistanceLong": 7,
    "ProperRunningStyleNige": 1,
    "ProperRunningStyleSenko": 7,
    "ProperRunningStyleSashi": 7,
    "ProperRunningStyleOikomi": 5,
    "ProperGroundTurf": 7,
    "ProperGroundDirt": 1
  },
  {
    "Id": 100201,
    "Rarity": 3,
    "RaceDressId": "100201",
    "ProperDistanceShort": 4,
    "ProperDistanceMile": 7,
    "ProperDistanceMiddle": 7,
    "ProperDistanceLong": 3,
    "ProperRunningStyleNige": 7,
    "ProperRunningStyleSenko": 5,
    "ProperRunningStyleSashi": 3,
    "ProperRunningStyleOikomi": 1,
    "ProperGroundTurf": 7,
    "ProperGroundDirt": 1
  },
  {
    "Id": 100301,
    "Rarity": 3,
    "RaceDressId": "100301",
    "ProperDistanceShort": 2,
    "ProperDistanceMile": 3,
    "ProperDistanceMiddle": 7,
    "ProperDistanceLong": 6,
    "ProperRunningStyleNige": 4,
    "ProperRunningStyleSenko": 7,
    "ProperRunningStyleSashi": 5,
    "ProperRunningStyleOikomi": 3,
    "ProperGroundTurf": 7,
    "ProperGroundDirt": 1
  },
  {
    "Id": 100302,
    "Rarity": 3,
    "RaceDressId": "100302",
    "ProperDistanceShort": 2,
    "ProperDistanceMile": 3,
    "ProperDistanceMiddle": 7,
    "ProperDistanceLong": 6,
    "ProperRunningStyleNige": 4,
    "ProperRunningStyleSenko": 7,
    "ProperRunningStyleSashi": 5,
    "ProperRunningStyleOikomi": 3,
    "ProperGroundTurf": 7,
    "ProperGroundDirt": 1
  },
  {
    "Id": 100401,
    "Rarity": 3,
    "RaceDressId": "100401",
    "ProperDistanceShort": 6,
    "ProperDistanceMile": 7,
    "ProperDistanceMiddle": 6,
    "ProperDistanceLong": 5,
    "ProperRunningStyleNige": 7,
    "ProperRunningStyleSenko": 3,
    "ProperRunningStyleSashi": 1,
    "ProperRunningStyleOikomi": 1,
    "ProperGroundTurf": 7,
    "ProperGroundDirt": 4
  },
  {
    "Id": 100402,
    "Rarity": 3,
    "RaceDressId": "100430",
    "ProperDistanceShort": 6,
    "ProperDistanceMile": 7,
    "ProperDistanceMiddle": 6,
    "ProperDistanceLong": 5,
    "ProperRunningStyleNige": 7,
    "ProperRunningStyleSenko": 3,
    "ProperRunningStyleSashi": 1,
    "ProperRunningStyleOikomi": 1,
    "ProperGroundTurf": 7,
    "ProperGroundDirt": 4
  },
  {
    "Id": 100501,
    "Rarity": 3,
    "RaceDressId": "100501",
    "ProperDistanceShort": 6,
    "ProperDistanceMile": 7,
    "ProperDistanceMiddle": 6,
    "ProperDistanceLong": 3,
    "ProperRunningStyleNige": 5,
    "ProperRunningStyleSenko": 7,
    "ProperRunningStyleSashi": 5,
    "ProperRunningStyleOikomi": 1,
    "ProperGroundTurf": 7,
    "ProperGroundDirt": 2
  },
  {
    "Id": 100502,
    "Rarity": 3,
    "RaceDressId": "100520",
    "ProperDistanceShort": 6,
    "ProperDistanceMile": 7,
    "ProperDistanceMiddle": 6,
    "ProperDistanceLong": 3,
    "ProperRunningStyleNige": 5,
    "ProperRunningStyleSenko": 7,
    "ProperRunningStyleSashi": 5,
    "ProperRunningStyleOikomi": 1,
    "ProperGroundTurf": 7,
    "ProperGroundDirt": 2
  },
  {
    "Id": 100601,
    "Rarity": 3,
    "RaceDressId": "100601",
    "ProperDistanceShort": 3,
    "ProperDistanceMile": 7,
    "ProperDistanceMiddle": 7,
    "ProperDistanceLong": 6,
    "ProperRunningStyleNige": 2,
    "ProperRunningStyleSenko": 7,
    "ProperRunningStyleSashi": 7,
    "ProperRunningStyleOikomi": 4,
    "ProperGroundTurf": 7,
    "ProperGroundDirt": 6
  },
  {
    "Id": 100602,
    "Rarity": 3,
    "RaceDressId": "100646",
    "ProperDistanceShort": 3,
    "ProperDistanceMile": 7,
    "ProperDistanceMiddle": 7,
    "ProperDistanceLong": 6,
    "ProperRunningStyleNige": 2,
    "ProperRunningStyleSenko": 7,
    "ProperRunningStyleSashi": 7,
    "ProperRunningStyleOikomi": 4,
    "ProperGroundTurf": 7,
    "ProperGroundDirt": 6
  },
  {
    "Id": 100701,
    "Rarity": 2,
    "RaceDressId": "000101",
    "ProperDistanceShort": 1,
    "ProperDistanceMile": 5,
    "ProperDistanceMiddle": 7,
    "ProperDistanceLong": 7,
    "ProperRunningStyleNige": 1,
    "ProperRunningStyleSenko": 6,
    "ProperRunningStyleSashi": 6,
    "ProperRunningStyleOikomi": 7,
    "ProperGroundTurf": 7,
    "ProperGroundDirt": 1
  },
  {
    "Id": 100801,
    "Rarity": 2,
    "RaceDressId": "000101",
    "ProperDistanceShort": 2,
    "ProperDistanceMile": 7,
    "ProperDistanceMiddle": 7,
    "ProperDistanceLong": 2,
    "ProperRunningStyleNige": 5,
    "ProperRunningStyleSenko": 6,
    "ProperRunningStyleSashi": 7,
    "ProperRunningStyleOikomi": 2,
    "ProperGroundTurf": 7,
    "ProperGroundDirt": 1
  },
  {
    "Id": 100901,
    "Rarity": 2,
    "RaceDressId": "000101",
    "ProperDistanceShort": 2,
    "ProperDistanceMile": 7,
    "ProperDistanceMiddle": 7,
    "ProperDistanceLong": 6,
    "ProperRunningStyleNige": 7,
    "ProperRunningStyleSenko": 7,
    "ProperRunningStyleSashi": 3,
    "ProperRunningStyleOikomi": 1,
    "ProperGroundTurf": 7,
    "ProperGroundDirt": 1
  },
  {
    "Id": 101001,
    "Rarity": 3,
    "RaceDressId": "101001",
    "ProperDistanceShort": 7,
    "ProperDistanceMile": 7,
    "ProperDistanceMiddle": 3,
    "ProperDistanceLong": 1,
    "ProperRunningStyleNige": 5,
    "ProperRunningStyleSenko": 7,
    "ProperRunningStyleSashi": 3,
    "ProperRunningStyleOikomi": 1,
    "ProperGroundTurf": 7,
    "ProperGroundDirt": 6
  },
  {
    "Id": 101101,
    "Rarity": 2,
    "RaceDressId": "000101",
    "ProperDistanceShort": 1,
    "ProperDistanceMile": 7,
    "ProperDistanceMiddle": 6,
    "ProperDistanceLong": 7,
    "ProperRunningStyleNige": 2,
    "ProperRunningStyleSenko": 7,
    "ProperRunningStyleSashi": 7,
    "ProperRunningStyleOikomi": 2,
    "ProperGroundTurf": 7,
    "ProperGroundDirt": 1
  },
  {
    "Id": 101102,
    "Rarity": 3,
    "RaceDressId": "101116",
    "ProperDistanceShort": 1,
    "ProperDistanceMile": 7,
    "ProperDistanceMiddle": 6,
    "ProperDistanceLong": 7,
    "ProperRunningStyleNige": 2,
    "ProperRunningStyleSenko": 7,
    "ProperRunningStyleSashi": 7,
    "ProperRunningStyleOikomi": 2,
    "ProperGroundTurf": 7,
    "ProperGroundDirt": 1
  },
  {
    "Id": 101201,
    "Rarity": 3,
    "RaceDressId": "101201",
    "ProperDistanceShort": 4,
    "ProperDistanceMile": 7,
    "ProperDistanceMiddle": 7,
    "ProperDistanceLong": 6,
    "ProperRunningStyleNige": 1,
    "ProperRunningStyleSenko": 6,
    "ProperRunningStyleSashi": 5,
    "ProperRunningStyleOikomi": 7,
    "ProperGroundTurf": 7,
    "ProperGroundDirt": 3
  },
  {
    "Id": 101301,
    "Rarity": 3,
    "RaceDressId": "101301",
    "ProperDistanceShort": 1,
    "ProperDistanceMile": 2,
    "ProperDistanceMiddle": 7,
    "ProperDistanceLong": 7,
    "ProperRunningStyleNige": 6,
    "ProperRunningStyleSenko": 7,
    "ProperRunningStyleSashi": 4,
    "ProperRunningStyleOikomi": 2,
    "ProperGroundTurf": 7,
    "ProperGroundDirt": 3
  },
  {
    "Id": 101302,
    "Rarity": 3,
    "RaceDressId": "101302",
    "ProperDistanceShort": 1,
    "ProperDistanceMile": 2,
    "ProperDistanceMiddle": 7,
    "ProperDistanceLong": 7,
    "ProperRunningStyleNige": 6,
    "ProperRunningStyleSenko": 7,
    "ProperRunningStyleSashi": 4,
    "ProperRunningStyleOikomi": 2,
    "ProperGroundTurf": 7,
    "ProperGroundDirt": 3
  },
  {
    "Id": 101401,
    "Rarity": 2,
    "RaceDressId": "000101",
    "ProperDistanceShort": 2,
    "ProperDistanceMile": 7,
    "ProperDistanceMiddle": 7,
    "ProperDistanceLong": 6,
    "ProperRunningStyleNige": 3,
    "ProperRunningStyleSenko": 7,
    "ProperRunningStyleSashi": 7,
    "ProperRunningStyleOikomi": 5,
    "ProperGroundTurf": 7,
    "ProperGroundDirt": 6
  },
  {
    "Id": 101402,
    "Rarity": 3,
    "RaceDressId": "101416",
    "ProperDistanceShort": 2,
    "ProperDistanceMile": 7,
    "ProperDistanceMiddle": 7,
    "ProperDistanceLong": 6,
    "ProperRunningStyleNige": 3,
    "ProperRunningStyleSenko": 7,
    "ProperRunningStyleSashi": 7,
    "ProperRunningStyleOikomi": 5,
    "ProperGroundTurf": 7,
    "ProperGroundDirt": 6
  },
  {
    "Id": 101501,
    "Rarity": 3,
    "RaceDressId": "101501",
    "ProperDistanceShort": 1,
    "ProperDistanceMile": 3,
    "ProperDistanceMiddle": 7,
    "ProperDistanceLong": 7,
    "ProperRunningStyleNige": 5,
    "ProperRunningStyleSenko": 7,
    "ProperRunningStyleSashi": 7,
    "ProperRunningStyleOikomi": 1,
    "ProperGroundTurf": 7,
    "ProperGroundDirt": 3
  },
  {
    "Id": 101502,
    "Rarity": 3,
    "RaceDressId": "101510",
    "ProperDistanceShort": 1,
    "ProperDistanceMile": 3,
    "ProperDistanceMiddle": 7,
    "ProperDistanceLong": 7,
    "ProperRunningStyleNige": 5,
    "ProperRunningStyleSenko": 7,
    "ProperRunningStyleSashi": 7,
    "ProperRunningStyleOikomi": 1,
    "ProperGroundTurf": 7,
    "ProperGroundDirt": 3
  },
  {
    "Id": 101601,
    "Rarity": 3,
    "RaceDressId": "101601",
    "ProperDistanceShort": 2,
    "ProperDistanceMile": 6,
    "ProperDistanceMiddle": 7,
    "ProperDistanceLong": 7,
    "ProperRunningStyleNige": 1,
    "ProperRunningStyleSenko": 7,
    "ProperRunningStyleSashi": 7,
    "ProperRunningStyleOikomi": 4,
    "ProperGroundTurf": 7,
    "ProperGroundDirt": 1
  },
  {
    "Id": 101701,
    "Rarity": 3,
    "RaceDressId": "101701",
    "ProperDistanceShort": 3,
    "ProperDistanceMile": 5,
    "ProperDistanceMiddle": 7,
    "ProperDistanceLong": 7,
    "ProperRunningStyleNige": 6,
    "ProperRunningStyleSenko": 7,
    "ProperRunningStyleSashi": 7,
    "ProperRunningStyleOikomi": 5,
    "ProperGroundTurf": 7,
    "ProperGroundDirt": 1
  },
  {
    "Id": 101702,
    "Rarity": 3,
    "RaceDressId": "101743",
    "ProperDistanceShort": 3,
    "ProperDistanceMile": 5,
    "ProperDistanceMiddle": 7,
    "ProperDistanceLong": 7,
    "ProperRunningStyleNige": 6,
    "ProperRunningStyleSenko": 7,
    "ProperRunningStyleSashi": 7,
    "ProperRunningStyleOikomi": 5,
    "ProperGroundTurf": 7,
    "ProperGroundDirt": 1
  },
  {
    "Id": 101801,
    "Rarity": 2,
    "RaceDressId": "000101",
    "ProperDistanceShort": 5,
    "ProperDistanceMile": 6,
    "ProperDistanceMiddle": 7,
    "ProperDistanceLong": 3,
    "ProperRunningStyleNige": 4,
    "ProperRunningStyleSenko": 7,
    "ProperRunningStyleSashi": 7,
    "ProperRunningStyleOikomi": 1,
    "ProperGroundTurf": 7,
    "ProperGroundDirt": 1
  },
  {
    "Id": 101802,
    "Rarity": 3,
    "RaceDressId": "101826",
    "ProperDistanceShort": 5,
    "ProperDistanceMile": 6,
    "ProperDistanceMiddle": 7,
    "ProperDistanceLong": 3,
    "ProperRunningStyleNige": 4,
    "ProperRunningStyleSenko": 7,
    "ProperRunningStyleSashi": 7,
    "ProperRunningStyleOikomi": 1,
    "ProperGroundTurf": 7,
    "ProperGroundDirt": 1
  },
  {
    "Id": 101901,
    "Rarity": 3,
    "RaceDressId": "101901",
    "ProperDistanceShort": 2,
    "ProperDistanceMile": 7,
    "ProperDistanceMiddle": 7,
    "ProperDistanceLong": 1,
    "ProperRunningStyleNige": 1,
    "ProperRunningStyleSenko": 7,
    "ProperRunningStyleSashi": 7,
    "ProperRunningStyleOikomi": 6,
    "ProperGroundTurf": 7,
    "ProperGroundDirt": 7
  },
  {
    "Id": 102001,
    "Rarity": 3,
    "RaceDressId": "102001",
    "ProperDistanceShort": 1,
    "ProperDistanceMile": 5,
    "ProperDistanceMiddle": 7,
    "ProperDistanceLong": 7,
    "ProperRunningStyleNige": 7,
    "ProperRunningStyleSenko": 6,
    "ProperRunningStyleSashi": 4,
    "ProperRunningStyleOikomi": 3,
    "ProperGroundTurf": 7,
    "ProperGroundDirt": 1
  },
  {
    "Id": 102002,
    "Rarity": 3,
    "RaceDressId": "102020",
    "ProperDistanceShort": 1,
    "ProperDistanceMile": 5,
    "ProperDistanceMiddle": 7,
    "ProperDistanceLong": 7,
    "ProperRunningStyleNige": 7,
    "ProperRunningStyleSenko": 6,
    "ProperRunningStyleSashi": 4,
    "ProperRunningStyleOikomi": 3,
    "ProperGroundTurf": 7,
    "ProperGroundDirt": 1
  },
  {
    "Id": 102101,
    "Rarity": 3,
    "RaceDressId": "102101",
    "ProperDistanceShort": 1,
    "ProperDistanceMile": 3,
    "ProperDistanceMiddle": 7,
    "ProperDistanceLong": 7,
    "ProperRunningStyleNige": 1,
    "ProperRunningStyleSenko": 7,
    "ProperRunningStyleSashi": 7,
    "ProperRunningStyleOikomi": 7,
    "ProperGroundTurf": 7,
    "ProperGroundDirt": 2
  },
  {
    "Id": 102201,
    "Rarity": 3,
    "RaceDressId": "102201",
    "ProperDistanceShort": 2,
    "ProperDistanceMile": 7,
    "ProperDistanceMiddle": 7,
    "ProperDistanceLong": 5,
    "ProperRunningStyleNige": 4,
    "ProperRunningStyleSenko": 7,
    "ProperRunningStyleSashi": 3,
    "ProperRunningStyleOikomi": 5,
    "ProperGroundTurf": 7,
    "ProperGroundDirt": 1
  },
  {
    "Id": 102301,
    "Rarity": 3,
    "RaceDressId": "102301",
    "ProperDistanceShort": 2,
    "ProperDistanceMile": 5,
    "ProperDistanceMiddle": 7,
    "ProperDistanceLong": 7,
    "ProperRunningStyleNige": 3,
    "ProperRunningStyleSenko": 7,
    "ProperRunningStyleSashi": 6,
    "ProperRunningStyleOikomi": 3,
    "ProperGroundTurf": 7,
    "ProperGroundDirt": 2
  },
  {
    "Id": 102302,
    "Rarity": 3,
    "RaceDressId": "102346",
    "ProperDistanceShort": 2,
    "ProperDistanceMile": 5,
    "ProperDistanceMiddle": 7,
    "ProperDistanceLong": 7,
    "ProperRunningStyleNige": 3,
    "ProperRunningStyleSenko": 7,
    "ProperRunningStyleSashi": 6,
    "ProperRunningStyleOikomi": 3,
    "ProperGroundTurf": 7,
    "ProperGroundDirt": 2
  },
  {
    "Id": 102401,
    "Rarity": 2,
    "RaceDressId": "000101",
    "ProperDistanceShort": 4,
    "ProperDistanceMile": 4,
    "ProperDistanceMiddle": 7,
    "ProperDistanceLong": 7,
    "ProperRunningStyleNige": 7,
    "ProperRunningStyleSenko": 7,
    "ProperRunningStyleSashi": 6,
    "ProperRunningStyleOikomi": 6,
    "ProperGroundTurf": 7,
    "ProperGroundDirt": 3
  },
  {
    "Id": 102402,
    "Rarity": 3,
    "RaceDressId": "102426",
    "ProperDistanceShort": 4,
    "ProperDistanceMile": 4,
    "ProperDistanceMiddle": 7,
    "ProperDistanceLong": 7,
    "ProperRunningStyleNige": 7,
    "ProperRunningStyleSenko": 7,
    "ProperRunningStyleSashi": 6,
    "ProperRunningStyleOikomi": 6,
    "ProperGroundTurf": 7,
    "ProperGroundDirt": 3
  },
  {
    "Id": 102501,
    "Rarity": 3,
    "RaceDressId": "102501",
    "ProperDistanceShort": 1,
    "ProperDistanceMile": 2,
    "ProperDistanceMiddle": 6,
    "ProperDistanceLong": 7,
    "ProperRunningStyleNige": 1,
    "ProperRunningStyleSenko": 5,
    "ProperRunningStyleSashi": 7,
    "ProperRunningStyleOikomi": 5,
    "ProperGroundTurf": 7,
    "ProperGroundDirt": 1
  },
  {
    "Id": 102601,
    "Rarity": 3,
    "RaceDressId": "102601",
    "ProperDistanceShort": 5,
    "ProperDistanceMile": 6,
    "ProperDistanceMiddle": 7,
    "ProperDistanceLong": 6,
    "ProperRunningStyleNige": 7,
    "ProperRunningStyleSenko": 3,
    "ProperRunningStyleSashi": 1,
    "ProperRunningStyleOikomi": 1,
    "ProperGroundTurf": 7,
    "ProperGroundDirt": 1
  },
  {
    "Id": 102602,
    "Rarity": 3,
    "RaceDressId": "102613",
    "ProperDistanceShort": 5,
    "ProperDistanceMile": 6,
    "ProperDistanceMiddle": 7,
    "ProperDistanceLong": 6,
    "ProperRunningStyleNige": 7,
    "ProperRunningStyleSenko": 3,
    "ProperRunningStyleSashi": 1,
    "ProperRunningStyleOikomi": 1,
    "ProperGroundTurf": 7,
    "ProperGroundDirt": 1
  },
  {
    "Id": 102701,
    "Rarity": 1,
    "RaceDressId": "000101",
    "ProperDistanceShort": 3,
    "ProperDistanceMile": 5,
    "ProperDistanceMiddle": 7,
    "ProperDistanceLong": 6,
    "ProperRunningStyleNige": 2,
    "ProperRunningStyleSenko": 7,
    "ProperRunningStyleSashi": 7,
    "ProperRunningStyleOikomi": 2,
    "ProperGroundTurf": 7,
    "ProperGroundDirt": 1
  },
  {
    "Id": 102801,
    "Rarity": 3,
    "RaceDressId": "102801",
    "ProperDistanceShort": 7,
    "ProperDistanceMile": 6,
    "ProperDistanceMiddle": 2,
    "ProperDistanceLong": 1,
    "ProperRunningStyleNige": 6,
    "ProperRunningStyleSenko": 7,
    "ProperRunningStyleSashi": 5,
    "ProperRunningStyleOikomi": 1,
    "ProperGroundTurf": 7,
    "ProperGroundDirt": 2
  },
  {
    "Id": 103001,
    "Rarity": 3,
    "RaceDressId": "103001",
    "ProperDistanceShort": 3,
    "ProperDistanceMile": 5,
    "ProperDistanceMiddle": 7,
    "ProperDistanceLong": 7,
    "ProperRunningStyleNige": 6,
    "ProperRunningStyleSenko": 7,
    "ProperRunningStyleSashi": 5,
    "ProperRunningStyleOikomi": 1,
    "ProperGroundTurf": 7,
    "ProperGroundDirt": 1
  },
  {
    "Id": 103002,
    "Rarity": 3,
    "RaceDressId": "103040",
    "ProperDistanceShort": 3,
    "ProperDistanceMile": 5,
    "ProperDistanceMiddle": 7,
    "ProperDistanceLong": 7,
    "ProperRunningStyleNige": 6,
    "ProperRunningStyleSenko": 7,
    "ProperRunningStyleSashi": 5,
    "ProperRunningStyleOikomi": 1,
    "ProperGroundTurf": 7,
    "ProperGroundDirt": 1
  },
  {
    "Id": 103101,
    "Rarity": 3,
    "RaceDressId": "103101",
    "ProperDistanceShort": 1,
    "ProperDistanceMile": 7,
    "ProperDistanceMiddle": 7,
    "ProperDistanceLong": 5,
    "ProperRunningStyleNige": 7,
    "ProperRunningStyleSenko": 5,
    "ProperRunningStyleSashi": 1,
    "ProperRunningStyleOikomi": 1,
    "ProperGroundTurf": 7,
    "ProperGroundDirt": 1
  },
  {
    "Id": 103201,
    "Rarity": 1,
    "RaceDressId": "000101",
    "ProperDistanceShort": 1,
    "ProperDistanceMile": 4,
    "ProperDistanceMiddle": 7,
    "ProperDistanceLong": 6,
    "ProperRunningStyleNige": 3,
    "ProperRunningStyleSenko": 7,
    "ProperRunningStyleSashi": 6,
    "ProperRunningStyleOikomi": 2,
    "ProperGroundTurf": 7,
    "ProperGroundDirt": 1
  },
  {
    "Id": 103301,
    "Rarity": 3,
    "RaceDressId": "103301",
    "ProperDistanceShort": 2,
    "ProperDistanceMile": 5,
    "ProperDistanceMiddle": 7,
    "ProperDistanceLong": 5,
    "ProperRunningStyleNige": 1,
    "ProperRunningStyleSenko": 1,
    "ProperRunningStyleSashi": 6,
    "ProperRunningStyleOikomi": 7,
    "ProperGroundTurf": 7,
    "ProperGroundDirt": 1
  },
  {
    "Id": 103501,
    "Rarity": 1,
    "RaceDressId": "000101",
    "ProperDistanceShort": 1,
    "ProperDistanceMile": 2,
    "ProperDistanceMiddle": 7,
    "ProperDistanceLong": 6,
    "ProperRunningStyleNige": 1,
    "ProperRunningStyleSenko": 6,
    "ProperRunningStyleSashi": 7,
    "ProperRunningStyleOikomi": 1,
    "ProperGroundTurf": 7,
    "ProperGroundDirt": 1
  },
  {
    "Id": 103701,
    "Rarity": 3,
    "RaceDressId": "103701",
    "ProperDistanceShort": 1,
    "ProperDistanceMile": 2,
    "ProperDistanceMiddle": 7,
    "ProperDistanceLong": 7,
    "ProperRunningStyleNige": 1,
    "ProperRunningStyleSenko": 6,
    "ProperRunningStyleSashi": 7,
    "ProperRunningStyleOikomi": 5,
    "ProperGroundTurf": 7,
    "ProperGroundDirt": 1
  },
  {
    "Id": 103702,
    "Rarity": 3,
    "RaceDressId": "103713",
    "ProperDistanceShort": 1,
    "ProperDistanceMile": 2,
    "ProperDistanceMiddle": 7,
    "ProperDistanceLong": 7,
    "ProperRunningStyleNige": 1,
    "ProperRunningStyleSenko": 6,
    "ProperRunningStyleSashi": 7,
    "ProperRunningStyleOikomi": 5,
    "ProperGroundTurf": 7,
    "ProperGroundDirt": 1
  },
  {
    "Id": 103801,
    "Rarity": 3,
    "RaceDressId": "103801",
    "ProperDistanceShort": 7,
    "ProperDistanceMile": 4,
    "ProperDistanceMiddle": 1,
    "ProperDistanceLong": 1,
    "ProperRunningStyleNige": 6,
    "ProperRunningStyleSenko": 7,
    "ProperRunningStyleSashi": 3,
    "ProperRunningStyleOikomi": 1,
    "ProperGroundTurf": 7,
    "ProperGroundDirt": 2
  },
  {
    "Id": 103901,
    "Rarity": 3,
    "RaceDressId": "103901",
    "ProperDistanceShort": 4,
    "ProperDistanceMile": 6,
    "ProperDistanceMiddle": 7,
    "ProperDistanceLong": 2,
    "ProperRunningStyleNige": 1,
    "ProperRunningStyleSenko": 5,
    "ProperRunningStyleSashi": 7,
    "ProperRunningStyleOikomi": 4,
    "ProperGroundTurf": 7,
    "ProperGroundDirt": 1
  },
  {
    "Id": 104001,
    "Rarity": 3,
    "RaceDressId": "104001",
    "ProperDistanceShort": 2,
    "ProperDistanceMile": 7,
    "ProperDistanceMiddle": 6,
    "ProperDistanceLong": 6,
    "ProperRunningStyleNige": 2,
    "ProperRunningStyleSenko": 7,
    "ProperRunningStyleSashi": 7,
    "ProperRunningStyleOikomi": 2,
    "ProperGroundTurf": 7,
    "ProperGroundDirt": 4
  },
  {
    "Id": 104002,
    "Rarity": 3,
    "RaceDressId": "104043",
    "ProperDistanceShort": 2,
    "ProperDistanceMile": 7,
    "ProperDistanceMiddle": 6,
    "ProperDistanceLong": 6,
    "ProperRunningStyleNige": 2,
    "ProperRunningStyleSenko": 7,
    "ProperRunningStyleSashi": 7,
    "ProperRunningStyleOikomi": 2,
    "ProperGroundTurf": 7,
    "ProperGroundDirt": 4
  },
  {
    "Id": 104101,
    "Rarity": 1,
    "RaceDressId": "000101",
    "ProperDistanceShort": 7,
    "ProperDistanceMile": 6,
    "ProperDistanceMiddle": 1,
    "ProperDistanceLong": 1,
    "ProperRunningStyleNige": 7,
    "ProperRunningStyleSenko": 7,
    "ProperRunningStyleSashi": 2,
    "ProperRunningStyleOikomi": 1,
    "ProperGroundTurf": 7,
    "ProperGroundDirt": 1
  },
  {
    "Id": 104501,
    "Rarity": 2,
    "RaceDressId": "000101",
    "ProperDistanceShort": 1,
    "ProperDistanceMile": 1,
    "ProperDistanceMiddle": 7,
    "ProperDistanceLong": 7,
    "ProperRunningStyleNige": 4,
    "ProperRunningStyleSenko": 7,
    "ProperRunningStyleSashi": 6,
    "ProperRunningStyleOikomi": 1,
    "ProperGroundTurf": 7,
    "ProperGroundDirt": 1
  },
  {
    "Id": 104502,
    "Rarity": 3,
    "RaceDressId": "104540",
    "ProperDistanceShort": 1,
    "ProperDistanceMile": 1,
    "ProperDistanceMiddle": 7,
    "ProperDistanceLong": 7,
    "ProperRunningStyleNige": 4,
    "ProperRunningStyleSenko": 7,
    "ProperRunningStyleSashi": 6,
    "ProperRunningStyleOikomi": 1,
    "ProperGroundTurf": 7,
    "ProperGroundDirt": 1
  },
  {
    "Id": 104601,
    "Rarity": 3,
    "RaceDressId": "104601",
    "ProperDistanceShort": 6,
    "ProperDistanceMile": 7,
    "ProperDistanceMiddle": 7,
    "ProperDistanceLong": 3,
    "ProperRunningStyleNige": 7,
    "ProperRunningStyleSenko": 4,
    "ProperRunningStyleSashi": 1,
    "ProperRunningStyleOikomi": 1,
    "ProperGroundTurf": 3,
    "ProperGroundDirt": 7
  },
  {
    "Id": 104801,
    "Rarity": 3,
    "RaceDressId": "104801",
    "ProperDistanceShort": 1,
    "ProperDistanceMile": 2,
    "ProperDistanceMiddle": 7,
    "ProperDistanceLong": 6,
    "ProperRunningStyleNige": 5,
    "ProperRunningStyleSenko": 7,
    "ProperRunningStyleSashi": 6,
    "ProperRunningStyleOikomi": 1,
    "ProperGroundTurf": 7,
    "ProperGroundDirt": 1
  },
  {
    "Id": 105001,
    "Rarity": 3,
    "RaceDressId": "105001",
    "ProperDistanceShort": 2,
    "ProperDistanceMile": 4,
    "ProperDistanceMiddle": 7,
    "ProperDistanceLong": 7,
    "ProperRunningStyleNige": 1,
    "ProperRunningStyleSenko": 2,
    "ProperRunningStyleSashi": 6,
    "ProperRunningStyleOikomi": 7,
    "ProperGroundTurf": 7,
    "ProperGroundDirt": 1
  },
  {
    "Id": 105101,
    "Rarity": 3,
    "RaceDressId": "105101",
    "ProperDistanceShort": 7,
    "ProperDistanceMile": 7,
    "ProperDistanceMiddle": 3,
    "ProperDistanceLong": 1,
    "ProperRunningStyleNige": 2,
    "ProperRunningStyleSenko": 7,
    "ProperRunningStyleSashi": 7,
    "ProperRunningStyleOikomi": 1,
    "ProperGroundTurf": 7,
    "ProperGroundDirt": 2
  },
  {
    "Id": 105201,
    "Rarity": 1,
    "RaceDressId": "000101",
    "ProperDistanceShort": 7,
    "ProperDistanceMile": 6,
    "ProperDistanceMiddle": 1,
    "ProperDistanceLong": 1,
    "ProperRunningStyleNige": 1,
    "ProperRunningStyleSenko": 1,
    "ProperRunningStyleSashi": 7,
    "ProperRunningStyleOikomi": 6,
    "ProperGroundTurf": 1,
    "ProperGroundDirt": 7
  },
  {
    "Id": 105202,
    "Rarity": 3,
    "RaceDressId": "105210",
    "ProperDistanceShort": 7,
    "ProperDistanceMile": 7,
    "ProperDistanceMiddle": 1,
    "ProperDistanceLong": 1,
    "ProperRunningStyleNige": 1,
    "ProperRunningStyleSenko": 1,
    "ProperRunningStyleSashi": 7,
    "ProperRunningStyleOikomi": 6,
    "ProperGroundTurf": 1,
    "ProperGroundDirt": 7
  },
  {
    "Id": 105601,
    "Rarity": 1,
    "RaceDressId": "000101",
    "ProperDistanceShort": 2,
    "ProperDistanceMile": 5,
    "ProperDistanceMiddle": 7,
    "ProperDistanceLong": 7,
    "ProperRunningStyleNige": 1,
    "ProperRunningStyleSenko": 6,
    "ProperRunningStyleSashi": 7,
    "ProperRunningStyleOikomi": 2,
    "ProperGroundTurf": 7,
    "ProperGroundDirt": 2
  },
  {
    "Id": 105602,
    "Rarity": 3,
    "RaceDressId": "105623",
    "ProperDistanceShort": 2,
    "ProperDistanceMile": 5,
    "ProperDistanceMiddle": 7,
    "ProperDistanceLong": 7,
    "ProperRunningStyleNige": 1,
    "ProperRunningStyleSenko": 6,
    "ProperRunningStyleSashi": 7,
    "ProperRunningStyleOikomi": 2,
    "ProperGroundTurf": 7,
    "ProperGroundDirt": 2
  },
  {
    "Id": 105801,
    "Rarity": 3,
    "RaceDressId": "105801",
    "ProperDistanceShort": 1,
    "ProperDistanceMile": 2,
    "ProperDistanceMiddle": 7,
    "ProperDistanceLong": 7,
    "ProperRunningStyleNige": 2,
    "ProperRunningStyleSenko": 7,
    "ProperRunningStyleSashi": 6,
    "ProperRunningStyleOikomi": 3,
    "ProperGroundTurf": 7,
    "ProperGroundDirt": 3
  },
  {
    "Id": 105901,
    "Rarity": 3,
    "RaceDressId": "105901",
    "ProperDistanceShort": 3,
    "ProperDistanceMile": 7,
    "ProperDistanceMiddle": 7,
    "ProperDistanceLong": 2,
    "ProperRunningStyleNige": 5,
    "ProperRunningStyleSenko": 6,
    "ProperRunningStyleSashi": 7,
    "ProperRunningStyleOikomi": 1,
    "ProperGroundTurf": 7,
    "ProperGroundDirt": 1
  },
  {
    "Id": 106001,
    "Rarity": 1,
    "RaceDressId": "000101",
    "ProperDistanceShort": 1,
    "ProperDistanceMile": 5,
    "ProperDistanceMiddle": 7,
    "ProperDistanceLong": 7,
    "ProperRunningStyleNige": 2,
    "ProperRunningStyleSenko": 6,
    "ProperRunningStyleSashi": 7,
    "ProperRunningStyleOikomi": 4,
    "ProperGroundTurf": 7,
    "ProperGroundDirt": 1
  },
  {
    "Id": 106002,
    "Rarity": 3,
    "RaceDressId": "106050",
    "ProperDistanceShort": 1,
    "ProperDistanceMile": 5,
    "ProperDistanceMiddle": 7,
    "ProperDistanceLong": 7,
    "ProperRunningStyleNige": 2,
    "ProperRunningStyleSenko": 6,
    "ProperRunningStyleSashi": 7,
    "ProperRunningStyleOikomi": 4,
    "ProperGroundTurf": 7,
    "ProperGroundDirt": 1
  },
  {
    "Id": 106101,
    "Rarity": 1,
    "RaceDressId": "000101",
    "ProperDistanceShort": 7,
    "ProperDistanceMile": 6,
    "ProperDistanceMiddle": 6,
    "ProperDistanceLong": 5,
    "ProperRunningStyleNige": 1,
    "ProperRunningStyleSenko": 6,
    "ProperRunningStyleSashi": 7,
    "ProperRunningStyleOikomi": 4,
    "ProperGroundTurf": 7,
    "ProperGroundDirt": 1
  },
  {
    "Id": 106102,
    "Rarity": 3,
    "RaceDressId": "106150",
    "ProperDistanceShort": 7,
    "ProperDistanceMile": 6,
    "ProperDistanceMiddle": 6,
    "ProperDistanceLong": 5,
    "ProperRunningStyleNige": 1,
    "ProperRunningStyleSenko": 6,
    "ProperRunningStyleSashi": 7,
    "ProperRunningStyleOikomi": 4,
    "ProperGroundTurf": 7,
    "ProperGroundDirt": 1
  },
  {
    "Id": 106201,
    "Rarity": 2,
    "RaceDressId": "000101",
    "ProperDistanceShort": 1,
    "ProperDistanceMile": 4,
    "ProperDistanceMiddle": 7,
    "ProperDistanceLong": 7,
    "ProperRunningStyleNige": 2,
    "ProperRunningStyleSenko": 7,
    "ProperRunningStyleSashi": 7,
    "ProperRunningStyleOikomi": 3,
    "ProperGroundTurf": 7,
    "ProperGroundDirt": 1
  },
  {
    "Id": 106401,
    "Rarity": 3,
    "RaceDressId": "106401",
    "ProperDistanceShort": 1,
    "ProperDistanceMile": 2,
    "ProperDistanceMiddle": 7,
    "ProperDistanceLong": 7,
    "ProperRunningStyleNige": 7,
    "ProperRunningStyleSenko": 3,
    "ProperRunningStyleSashi": 2,
    "ProperRunningStyleOikomi": 1,
    "ProperGroundTurf": 7,
    "ProperGroundDirt": 1
  },
  {
    "Id": 106701,
    "Rarity": 3,
    "RaceDressId": "106701",
    "ProperDistanceShort": 1,
    "ProperDistanceMile": 5,
    "ProperDistanceMiddle": 7,
    "ProperDistanceLong": 7,
    "ProperRunningStyleNige": 1,
    "ProperRunningStyleSenko": 6,
    "ProperRunningStyleSashi": 7,
    "ProperRunningStyleOikomi": 4,
    "ProperGroundTurf": 7,
    "ProperGroundDirt": 1
  },
  {
    "Id": 106801,
    "Rarity": 3,
    "RaceDressId": "106801",
    "ProperDistanceShort": 3,
    "ProperDistanceMile": 5,
    "ProperDistanceMiddle": 7,
    "ProperDistanceLong": 7,
    "ProperRunningStyleNige": 7,
    "ProperRunningStyleSenko": 6,
    "ProperRunningStyleSashi": 5,
    "ProperRunningStyleOikomi": 1,
    "ProperGroundTurf": 7,
    "ProperGroundDirt": 1
  },
  {
    "Id": 106901,
    "Rarity": 3,
    "RaceDressId": "106901",
    "ProperDistanceShort": 3,
    "ProperDistanceMile": 7,
    "ProperDistanceMiddle": 7,
    "ProperDistanceLong": 3,
    "ProperRunningStyleNige": 6,
    "ProperRunningStyleSenko": 7,
    "ProperRunningStyleSashi": 2,
    "ProperRunningStyleOikomi": 1,
    "ProperGroundTurf": 7,
    "ProperGroundDirt": 1
  },
  {
    "Id": 107101,
    "Rarity": 3,
    "RaceDressId": "107101",
    "ProperDistanceShort": 3,
    "ProperDistanceMile": 6,
    "ProperDistanceMiddle": 7,
    "ProperDistanceLong": 4,
    "ProperRunningStyleNige": 5,
    "ProperRunningStyleSenko": 7,
    "ProperRunningStyleSashi": 4,
    "ProperRunningStyleOikomi": 1,
    "ProperGroundTurf": 7,
    "ProperGroundDirt": 2
  },
  {
    "Id": 107201,
    "Rarity": 3,
    "RaceDressId": "107201",
    "ProperDistanceShort": 1,
    "ProperDistanceMile": 6,
    "ProperDistanceMiddle": 7,
    "ProperDistanceLong": 3,
    "ProperRunningStyleNige": 2,
    "ProperRunningStyleSenko": 7,
    "ProperRunningStyleSashi": 7,
    "ProperRunningStyleOikomi": 1,
    "ProperGroundTurf": 7,
    "ProperGroundDirt": 3
  },
  {
    "Id": 107401,
    "Rarity": 3,
    "RaceDressId": "107401",
    "ProperDistanceShort": 2,
    "ProperDistanceMile": 5,
    "ProperDistanceMiddle": 7,
    "ProperDistanceLong": 7,
    "ProperRunningStyleNige": 1,
    "ProperRunningStyleSenko": 4,
    "ProperRunningStyleSashi": 7,
    "ProperRunningStyleOikomi": 7,
    "ProperGroundTurf": 7,
    "ProperGroundDirt": 1
  }
]